countrygroups/__init__.py
countrygroups/_version.py
countrygroups-0.13.0.dist-info/METADATA
countrygroups-0.13.0.dist-info/WHEEL
countrygroups-0.13.0.dist-info/top_level.txt
countrygroups-0.13.0.dist-info/RECORD
