Metadata-Version: 2.1
Name: countrygroups
Version: 0.13.0
Summary: Country groups as lists of ISO codes, especially those related to the UNFCCC climate policy process
Home-page: https://github.com/openclimatedata/countrygroups
Author: Robert Gieseke
Author-email: robert.gieseke@pik-potsdam.de
License: CC0
Keywords: country code,country groups,unfccc,climate change
Platform: any
Classifier: Development Status :: 3 - Alpha
Classifier: Intended Audience :: Developers
Classifier: Operating System :: OS Independent
Classifier: Programming Language :: Python :: 2.7
Classifier: Programming Language :: Python :: 3.4
Classifier: Programming Language :: Python :: 3.5
Classifier: Programming Language :: Python :: 3.6
Requires-Dist: shortcountrynames
